mollie/__init__.py
mollie/_hooks/__init__.py
mollie/_hooks/mollie_hooks.py
mollie/_hooks/registration.py
mollie/_hooks/sdkhooks.py
mollie/_hooks/types.py
mollie/_version.py
mollie/balance_transfers.py
mollie/balances.py
mollie/basesdk.py
mollie/capabilities.py
mollie/captures.py
mollie/chargebacks_sdk.py
mollie/client_links.py
mollie/clients.py
mollie/customers.py
mollie/delayed_routing.py
mollie/httpclient.py
mollie/invoices.py
mollie/mandates.py
mollie/methods.py
mollie/models/__init__.py
mollie/models/address.py
mollie/models/amount.py
mollie/models/amount_nullable.py
mollie/models/apierror.py
mollie/models/balance_card_audience.py
mollie/models/balance_card_issuer.py
mollie/models/balance_card_region.py
mollie/models/balance_fee_type.py
mollie/models/balance_prepayment_part_type.py
mollie/models/balance_report_grouping.py
mollie/models/balance_transaction_type.py
mollie/models/balance_transfer_category.py
mollie/models/balance_transfer_category_response.py
mollie/models/balance_transfer_destination_type.py
mollie/models/balance_transfer_party_type.py
mollie/models/balance_transfer_party_type_response.py
mollie/models/balance_transfer_status.py
mollie/models/balance_transfer_status_reason_response.py
mollie/models/billingaddress.py
mollie/models/cancel_paymentop.py
mollie/models/cancel_refundop.py
mollie/models/cancel_subscriptionop.py
mollie/models/capability_requirement_status.py
mollie/models/capability_status.py
mollie/models/capability_status_reason.py
mollie/models/capture_mode.py
mollie/models/capture_mode_response.py
mollie/models/capture_response.py
mollie/models/client_link_request.py
mollie/models/client_link_response.py
mollie/models/clienterror.py
mollie/models/components_sub_totals.py
mollie/models/create_captureop.py
mollie/models/create_client_linkop.py
mollie/models/create_connect_balance_transferop.py
mollie/models/create_customer_paymentop.py
mollie/models/create_customerop.py
mollie/models/create_mandateop.py
mollie_api_python_beta-0.58.6.dist-info/METADATA
mollie_api_python_beta-0.58.6.dist-info/WHEEL
mollie_api_python_beta-0.58.6.dist-info/licenses/LICENSE.md
mollie_api_python_beta-0.58.6.dist-info/RECORD
